hoppysearch/__init__.py
hoppysearch/api_client.py
hoppysearch/configuration.py
hoppysearch/dictToClass.py
hoppysearch/hs_api.py
hoppysearch/rest.py
hoppysearch/api/__init__.py
hoppysearch/api/general_api.py
hoppysearch/models/__init__.py
hoppysearch-0.0.13.dist-info/METADATA
hoppysearch-0.0.13.dist-info/WHEEL
hoppysearch-0.0.13.dist-info/licenses/LICENSE
hoppysearch-0.0.13.dist-info/RECORD
