Metadata-Version: 2.1
Name: hoppysearch
Version: 0.0.13
Summary: Hoppysearch Search JavaScript Client
Project-URL: Homepage, https://github.com/Hoppysoft-pvt/hoppysearch-python-client.git
Author-email: Pragyan Satapathy <pragyan@hoppysoft.com>
License-File: LICENSE
Classifier: License :: OSI Approved :: MIT License
Classifier: Operating System :: OS Independent
Classifier: Programming Language :: Python :: 3
Requires-Python: >=3.7
